multiview_stitcher/__init__.py
multiview_stitcher/_version.py
multiview_stitcher/czi_utils.py
multiview_stitcher/czifile_patch.py
multiview_stitcher/fusion.py
multiview_stitcher/io.py
multiview_stitcher/misc_utils.py
multiview_stitcher/msi_utils.py
multiview_stitcher/mv_graph.py
multiview_stitcher/ngff_utils.py
multiview_stitcher/param_utils.py
multiview_stitcher/registration.py
multiview_stitcher/sample_data.py
multiview_stitcher/spatial_image_utils.py
multiview_stitcher/transformation.py
multiview_stitcher/transforms.py
multiview_stitcher/vis_utils.py
multiview_stitcher/weights.py
multiview_stitcher/_benchmarks/__init__.py
multiview_stitcher/_benchmarks/test_core.py
multiview_stitcher/_tests/__init__.py
multiview_stitcher/_tests/_create_test_params.ipynb
multiview_stitcher/_tests/test_bench.py
multiview_stitcher/_tests/test_fusion.py
multiview_stitcher/_tests/test_integration.py
multiview_stitcher/_tests/test_io.py
multiview_stitcher/_tests/test_msi_utils.py
multiview_stitcher/_tests/test_mv_graph.py
multiview_stitcher/_tests/test_ngff_utils.py
multiview_stitcher/_tests/test_param_utils.py
multiview_stitcher/_tests/test_quickstart.py
multiview_stitcher/_tests/test_registration.py
multiview_stitcher/_tests/test_sample_data.py
multiview_stitcher/_tests/test_spatial_image_utils.py
multiview_stitcher/_tests/test_vis_utils.py
multiview_stitcher/_tests/test_weights.py
multiview_stitcher/_tests/quickstart/0_data_preparation.py
multiview_stitcher/_tests/quickstart/1_registration.py
multiview_stitcher/_tests/quickstart/2_fusion.py
multiview_stitcher/_tests/quickstart/3_fusion_large.py
multiview_stitcher/test-datasets/mosaic_test.czi
multiview_stitcher-0.1.45.dist-info/licenses/LICENSE
multiview_stitcher-0.1.45.dist-info/METADATA
multiview_stitcher-0.1.45.dist-info/WHEEL
multiview_stitcher-0.1.45.dist-info/top_level.txt
multiview_stitcher-0.1.45.dist-info/RECORD
