Metadata-Version: 2.4
Name: multiview-stitcher
Version: 0.1.45
Summary: Registration and fusion of large imaging datasets in 2D and 3D.
Author-email: Marvin Albert <marvin.albert@gmail.com>
License: BSD 3-Clause
Project-URL: Bug Tracker, https://github.com/multiview-stitcher/multiview-stitcher/issues
Project-URL: Documentation, https://multiview-stitcher.github.io/multiview-stitcher/
Project-URL: Source Code, https://github.com/multiview-stitcher/multiview-stitcher
Project-URL: User Support, https://github.com/multiview-stitcher/multiview-stitcher/issues
Classifier: Development Status :: 2 - Pre-Alpha
Classifier: Environment :: X11 Applications :: Qt
Classifier: Intended Audience :: Education
Classifier: Intended Audience :: Science/Research
Classifier: Intended Audience :: Developers
Classifier: License :: OSI Approved :: BSD License
Classifier: Programming Language :: Python
Classifier: Programming Language :: Python :: 3 :: Only
Classifier: Programming Language :: Python :: 3.10
Classifier: Programming Language :: Python :: 3.11
Classifier: Programming Language :: Python :: 3.12
Classifier: Programming Language :: Python :: 3.13
Classifier: Topic :: Scientific/Engineering
Classifier: Topic :: Scientific/Engineering :: Image Processing
Classifier: Topic :: Scientific/Engineering :: Information Analysis
Classifier: Topic :: Scientific/Engineering :: Bio-Informatics
Classifier: Topic :: Utilities
Classifier: Operating System :: OS Independent
Requires-Python: >=3.10
License-File: LICENSE
Requires-Dist: numpy>=1.18
Requires-Dist: dask<2025.11.0
Requires-Dist: dask_image
Requires-Dist: zarr
Requires-Dist: xarray>=2024.10.0
Requires-Dist: tifffile>=2022.7.28
Requires-Dist: networkx
Requires-Dist: tqdm
Requires-Dist: matplotlib
Requires-Dist: scikit-image>=0.21.0
Requires-Dist: spatial_image==1.2.3
Requires-Dist: multiscale_spatial_image==2.0.3
Requires-Dist: ngff-zarr>=0.12.2
Requires-Dist: ome-zarr>=0.10.2
Provides-Extra: ants
Requires-Dist: antspyx>=0.6.0; extra == "ants"
Provides-Extra: czi
Requires-Dist: czifile==2019.7.2.1; extra == "czi"
Requires-Dist: imagecodecs>=2023.7.10; extra == "czi"
Provides-Extra: dev
Requires-Dist: tox; extra == "dev"
Requires-Dist: jupyter; extra == "dev"
Requires-Dist: pytest<8.0.0; extra == "dev"
Requires-Dist: pytest-cov; extra == "dev"
Requires-Dist: pytest-benchmark>5; extra == "dev"
Requires-Dist: nbmake; extra == "dev"
Requires-Dist: antspyx>=0.6.0; extra == "dev"
Requires-Dist: czifile==2019.7.2.1; extra == "dev"
Requires-Dist: imagecodecs>=2023.7.10; extra == "dev"
Requires-Dist: pre-commit; extra == "dev"
Dynamic: license-file
